{"vegetarian": true, "vegan": false, "glutenFree": true, "dairyFree": false, "veryHealthy": false, "cheap": false, "veryPopular": false, "sustainable": false, "weightWatcherSmartPoints": 4, "gaps": "no", "lowFodmap": false, "ketogenic": false, "whole30": false, "preparationMinutes": 15, "cookingMinutes": 10, "sourceUrl": "http://www.ohsweetbasil.com/2015/01/aussie-bites-copycat-recipe.html", "spoonacularSourceUrl": "https://spoonacular.com/aussie-bites-copycat-626179", "aggregateLikes": 24, "spoonacularScore": 20.0, "healthScore": 1.0, "creditText": "Oh Sweet Basil", "sourceName": "Oh Sweet Basil", "pricePerServing": 21.94, "extendedIngredients": [{"id": 18372, "aisle": "Baking", "image": "white-powder.jpg", "consitency": "solid", "name": "baking soda", "original": "1\u00bd teaspoons baking soda", "originalString": "1\u00bd teaspoons baking soda", "originalName": "baking soda", "amount": 1.5, "unit": "teaspoons", "meta": [], "metaInformation": [], "measures": {"us": {"amount": 1.5, "unitShort": "tsps", "unitLong": "teaspoons"}, "metric": {"amount": 1.5, "unitShort": "tsps", "unitLong": "teaspoons"}}}, {"id": 1001, "aisle": "Milk, Eggs, Other Dairy", "image": "butter-sliced.jpg", "consitency": "solid", "name": "butter", "original": "\u00bd cup butter, softened", "originalString": "\u00bd cup butter, softened", "originalName": "butter, softened", "amount": 0.5, "unit": "cup", "meta": ["softened"], "metaInformation": ["softened"], "measures": {"us": {"amount": 0.5, "unitShort": "cups", "unitLong": "cups"}, "metric": {"amount": 118.294, "unitShort": "g", "unitLong": "grams"}}}, {"id": 4582, "aisle": "Oil, Vinegar, Salad Dressing", "image": "vegetable-oil.jpg", "consitency": "liquid", "name": "canola oil", "original": "\u00bd cup canola oil", "originalString": "\u00bd cup canola oil", "originalName": "canola oil", "amount": 0.5, "unit": "cup", "meta": [], "metaInformation": [], "measures": {"us": {"amount": 0.5, "unitShort": "cups", "unitLong": "cups"}, "metric": {"amount": 118.294, "unitShort": "g", "unitLong": "grams"}}}, {"id": 12006, "aisle": "Health Foods", "image": "chia-seeds.jpg", "consitency": "solid", "name": "chia seeds", "original": "1 tablespoon chia seeds", "originalString": "1 tablespoon chia seeds", "originalName": "chia seeds", "amount": 1.0, "unit": "tablespoon", "meta": [], "metaInformation": [], "measures": {"us": {"amount": 1.0, "unitShort": "Tbsp", "unitLong": "Tbsp"}, "metric": {"amount": 1.0, "unitShort": "Tbsp", "unitLong": "Tbsp"}}}, {"id": 12108, "aisle": "Baking", "image": "coconut-flakes.png", "consitency": "solid", "name": "coconut flakes", "original": "1 tablespoon coconut flakes", "originalString": "1 tablespoon coconut flakes", "originalName": "coconut flakes", "amount": 1.0, "unit": "tablespoon", "meta": [], "metaInformation": [], "measures": {"us": {"amount": 1.0, "unitShort": "Tbsp", "unitLong": "Tbsp"}, "metric": {"amount": 1.0, "unitShort": "Tbsp", "unitLong": "Tbsp"}}}, {"id": 9087, "aisle": "Dried Fruits;Produce", "image": "dates.jpg", "consitency": "solid", "name": "dates", "original": "\u00bd cup dates, pitted", "originalString": "\u00bd cup dates, pitted", "originalName": "dates, pitted", "amount": 0.5, "unit": "cup", "meta": ["pitted"], "metaInformation": ["pitted"], "measures": {"us": {"amount": 0.5, "unitShort": "cups", "unitLong": "cups"}, "metric": {"amount": 118.294, "unitShort": "g", "unitLong": "grams"}}}, {"id": 9032, "aisle": "Dried Fruits;Produce", "image": "dried-apricots.jpg", "consitency": "solid", "name": "dried apricots", "original": "\u00bd cup dried apricots", "originalString": "\u00bd cup dried apricots", "originalName": "dried apricots", "amount": 0.5, "unit": "cup", "meta": ["dried"], "metaInformation": ["dried"], "measures": {"us": {"amount": 0.5, "unitShort": "cups", "unitLong": "cups"}, "metric": {"amount": 118.294, "unitShort": "g", "unitLong": "grams"}}}, {"id": 20132, "aisle": "Gluten Free;Health Foods", "image": "brown-flour.jpg", "consitency": "solid", "name": "oat flour", "original": "2 cups oat flour", "originalString": "2 cups oat flour", "originalName": "oat flour", "amount": 2.0, "unit": "cups", "meta": [], "metaInformation": [], "measures": {"us": {"amount": 2.0, "unitShort": "cups", "unitLong": "cups"}, "metric": {"amount": 473.176, "unitShort": "g", "unitLong": "grams"}}}, {"id": 20035, "aisle": "Pasta and Rice;Health Foods", "image": "uncooked-quinoa.png", "consitency": "solid", "name": "quinoa", "original": "1/3 cup quinoa", "originalString": "1/3 cup quinoa", "originalName": "quinoa", "amount": 0.3333333333333333, "unit": "cup", "meta": [], "metaInformation": [], "measures": {"us": {"amount": 0.333, "unitShort": "cups", "unitLong": "cups"}, "metric": {"amount": 78.863, "unitShort": "g", "unitLong": "grams"}}}, {"id": 9299, "aisle": "Dried Fruits;Produce;Baking", "image": "raisins.jpg", "consitency": "solid", "name": "raisins", "original": "1/3 cup raisins", "originalString": "1/3 cup raisins", "originalName": "raisins", "amount": 0.3333333333333333, "unit": "cup", "meta": [], "metaInformation": [], "measures": {"us": {"amount": 0.333, "unitShort": "cups", "unitLong": "cups"}, "metric": {"amount": 78.863, "unitShort": "g", "unitLong": "grams"}}}, {"id": 8120, "aisle": "Cereal", "image": "rolled-oats.jpg", "consitency": "solid", "name": "rolled oats", "original": "2 cups rolled oats", "originalString": "2 cups rolled oats", "originalName": "rolled oats", "amount": 2.0, "unit": "cups", "meta": [], "metaInformation": [], "measures": {"us": {"amount": 2.0, "unitShort": "cups", "unitLong": "cups"}, "metric": {"amount": 473.176, "unitShort": "g", "unitLong": "grams"}}}, {"id": 1012047, "aisle": "Spices and Seasonings", "image": "salt.jpg", "consitency": "solid", "name": "sea salt", "original": "pinch of sea salt", "originalString": "pinch of sea salt", "originalName": "pinch of sea salt", "amount": 1.0, "unit": "pinch", "meta": [], "metaInformation": [], "measures": {"us": {"amount": 1.0, "unitShort": "pinch", "unitLong": "pinch"}, "metric": {"amount": 1.0, "unitShort": "pinch", "unitLong": "pinch"}}}, {"id": 93818, "aisle": "Savory Snacks", "image": "sunflower-seeds.jpg", "consitency": "solid", "name": "seeds", "original": "1 tablespoon pepitas or sun flower seeds", "originalString": "1 tablespoon pepitas or sun flower seeds", "originalName": "pepitas or sun flower seeds", "amount": 1.0, "unit": "tablespoon", "meta": [], "metaInformation": [], "measures": {"us": {"amount": 1.0, "unitShort": "Tbsp", "unitLong": "Tbsp"}, "metric": {"amount": 1.0, "unitShort": "Tbsp", "unitLong": "Tbsp"}}}, {"id": 19335, "aisle": "Baking", "image": "sugar-in-bowl.png", "consitency": "solid", "name": "sugar", "original": "2 tablespoons sugar", "originalString": "2 tablespoons sugar", "originalName": "sugar", "amount": 2.0, "unit": "tablespoons", "meta": [], "metaInformation": [], "measures": {"us": {"amount": 2.0, "unitShort": "Tbsps", "unitLong": "Tbsps"}, "metric": {"amount": 2.0, "unitShort": "Tbsps", "unitLong": "Tbsps"}}}], "id": 626179, "title": "Aussie Bites Copycat", "readyInMinutes": 25, "servings": 30, "image": "https://spoonacular.com/recipeImages/626179-556x370.jpg", "imageType": "jpg", "cuisines": [], "dishTypes": ["antipasti", "starter", "snack", "appetizer", "antipasto", "hor d'oeuvre"], "diets": ["gluten free", "lacto ovo vegetarian"], "occasions": [], "winePairing": {}, "instructions": "Preheat the oven to 350 degrees and spray a mini muffin tin with nonstick spray.In a food processor, pulse the dates and apricots until smooth.In a large bowl, combing all remaining ingredients and stir to combine. Press the dough into the muffin holes and bake for 10 minutes. Repeat with remaining dough and store in an airtight container.", "analyzedInstructions": [{"name": "", "steps": [{"number": 1, "step": "Preheat the oven to 350 degrees and spray a mini muffin tin with nonstick spray.In a food processor, pulse the dates and apricots until smooth.In a large bowl, combing all remaining ingredients and stir to combine. Press the dough into the muffin holes and bake for 10 minutes. Repeat with remaining dough and store in an airtight container.", "ingredients": [{"id": 9087, "name": "dates", "image": "dates.jpg"}], "equipment": [{"id": 405905, "name": "mini muffin tray", "image": "mini-muffin-tray.jpg"}, {"id": 404771, "name": "food processor", "image": "food-processor.png"}, {"id": 404783, "name": "bowl", "image": "bowl.jpg"}, {"id": 404784, "name": "oven", "image": "oven.jpg"}], "length": {"number": 10, "unit": "minutes"}}]}], "creditsText": "Oh Sweet Basil"}