{"vegetarian": true, "vegan": true, "glutenFree": true, "dairyFree": true, "veryHealthy": false, "cheap": false, "veryPopular": false, "sustainable": false, "weightWatcherSmartPoints": 58, "gaps": "no", "lowFodmap": true, "ketogenic": false, "whole30": false, "sourceUrl": "http://www.seriouseats.com/recipes/2013/03/chamomile-tequila-sour-cocktail-recipe-easy-spring-drink.html", "spoonacularSourceUrl": "https://spoonacular.com/chamomile-tequila-sour-204935", "aggregateLikes": 90, "spoonacularScore": 3.0, "healthScore": 0.0, "creditText": "Serious Eats", "sourceName": "Serious Eats", "pricePerServing": 417.27, "extendedIngredients": [{"id": 1082047, "aisle": "Spices and Seasonings", "image": "salt.jpg", "consitency": "solid", "name": "kosher salt", "original": "1/2 cup Kosher Salt", "originalString": "1/2 cup Kosher Salt", "originalName": "Kosher Salt", "amount": 0.5, "unit": "cup", "meta": [], "metaInformation": [], "measures": {"us": {"amount": 0.5, "unitShort": "cups", "unitLong": "cups"}, "metric": {"amount": 118.294, "unitShort": "g", "unitLong": "grams"}}}, {"id": 1029159, "aisle": "Produce", "image": "lime-wedge.jpg", "consitency": "solid", "name": "lime wedge", "original": "1 lime wedge, plus 1 ounce fresh lime juice from about 2 limes", "originalString": "1 lime wedge, plus 1 ounce fresh lime juice from about 2 limes", "originalName": "lime wedge, plus 1 ounce fresh lime juice from about 2 limes", "amount": 1.0, "unit": "", "meta": ["fresh"], "metaInformation": ["fresh"], "measures": {"us": {"amount": 1.0, "unitShort": "", "unitLong": ""}, "metric": {"amount": 1.0, "unitShort": "", "unitLong": ""}}}, {"id": 90480, "aisle": "Alcoholic Beverages", "image": "simple-syrup.jpg", "consitency": "liquid", "name": "simple syrup", "original": "1 1/2 ounces chamomile simple syrup", "originalString": "1 1/2 ounces chamomile simple syrup", "originalName": "chamomile simple syrup", "amount": 1.5, "unit": "ounces", "meta": [], "metaInformation": [], "measures": {"us": {"amount": 1.5, "unitShort": "oz", "unitLong": "ounces"}, "metric": {"amount": 42.524, "unitShort": "g", "unitLong": "grams"}}}, {"id": 19335, "aisle": "Baking", "image": "sugar-in-bowl.png", "consitency": "solid", "name": "sugar", "original": "1 cup sugar", "originalString": "1 cup sugar", "originalName": "sugar", "amount": 1.0, "unit": "cup", "meta": [], "metaInformation": [], "measures": {"us": {"amount": 1.0, "unitShort": "cup", "unitLong": "cup"}, "metric": {"amount": 236.588, "unitShort": "g", "unitLong": "grams"}}}, {"id": 10111111, "aisle": "Tea and Coffee", "image": "tea-bags.jpg", "consitency": "solid", "name": "tea bags", "original": "4 chamomile tea bags", "originalString": "4 chamomile tea bags", "originalName": "chamomile tea bags", "amount": 4.0, "unit": "", "meta": [], "metaInformation": [], "measures": {"us": {"amount": 4.0, "unitShort": "", "unitLong": ""}, "metric": {"amount": 4.0, "unitShort": "", "unitLong": ""}}}, {"id": 10814037, "aisle": "Alcoholic Beverages", "image": "tequila.png", "consitency": "liquid", "name": "tequila", "original": "1 3/4 ounces tequila", "originalString": "1 3/4 ounces tequila", "originalName": "tequila", "amount": 1.75, "unit": "ounces", "meta": [], "metaInformation": [], "measures": {"us": {"amount": 1.75, "unitShort": "oz", "unitLong": "ounces"}, "metric": {"amount": 49.612, "unitShort": "g", "unitLong": "grams"}}}, {"id": 14412, "aisle": "Beverages", "image": "water.png", "consitency": "liquid", "name": "water", "original": "1 cup water", "originalString": "1 cup water", "originalName": "water", "amount": 1.0, "unit": "cup", "meta": [], "metaInformation": [], "measures": {"us": {"amount": 1.0, "unitShort": "cup", "unitLong": "cup"}, "metric": {"amount": 236.588, "unitShort": "g", "unitLong": "grams"}}}], "id": 204935, "title": "Chamomile Tequila Sour", "readyInMinutes": 35, "servings": 1, "image": "https://spoonacular.com/recipeImages/204935-556x370.jpg", "imageType": "jpg", "cuisines": [], "dishTypes": [], "diets": ["gluten free", "dairy free", "lacto ovo vegetarian", "fodmap friendly", "vegan"], "occasions": [], "winePairing": {"pairedWines": [], "pairingText": "", "productMatches": []}, "instructions": "Procedures                                                                              1                                                                            For the Chamomile Simple Syrup: Combine water and sugar in a small saucepan over high heat. Stir to dissolve the sugar and bring to a boil. Immediately remove from heat and add the chamomile tea bags. Steep for 30 minutes then remove the tea. Cool to room temperature and refrigerate.                                                                                                                             2                                                                            For Each Cocktail: Place the salt in a small, shallow plate in an even layer. Moisten the rim of a coupe glass by running a lime wedge around the rim. Dip glass into salt and set aside.                                                                                                                             3                                                                            Combine lime juice, tequila, and chamomile simple syrup in a cocktail shaker. Fill with ice. Shake until well chilled, about 15 seconds. Strain into the salt rimmed coupe glass and serve.", "analyzedInstructions": [{"name": "For the Chamomile Simple Syrup", "steps": [{"number": 1, "step": "Combine water and sugar in a small saucepan over high heat. Stir to dissolve the sugar and bring to a boil. Immediately remove from heat and add the chamomile tea bags. Steep for 30 minutes then remove the tea. Cool to room temperature and refrigerate.", "ingredients": [{"id": 10111111, "name": "tea bag", "image": "tea-bags.jpg"}, {"id": 19335, "name": "sugar", "image": "sugar-in-bowl.png"}, {"id": 14412, "name": "water", "image": "water.png"}], "equipment": [{"id": 404669, "name": "sauce pan", "image": "sauce-pan.jpg"}], "length": {"number": 30, "unit": "minutes"}}]}, {"name": "For Each Cocktail", "steps": [{"number": 1, "step": "Place the salt in a small, shallow plate in an even layer. Moisten the rim of a coupe glass by running a lime wedge around the rim. Dip glass into salt and set aside.", "ingredients": [{"id": 1029159, "name": "lime wedge", "image": "lime-wedge.jpg"}, {"id": 2047, "name": "salt", "image": "salt.jpg"}], "equipment": []}, {"number": 2, "step": "Combine lime juice, tequila, and chamomile simple syrup in a cocktail shaker. Fill with ice. Shake until well chilled, about 15 seconds. Strain into the salt rimmed coupe glass and serve.", "ingredients": [{"id": 90480, "name": "simple syrup", "image": "simple-syrup.jpg"}, {"id": 10814037, "name": "tequila", "image": "tequila.png"}, {"id": 2047, "name": "salt", "image": "salt.jpg"}, {"id": 10014412, "name": "ice", "image": "ice-cubes.png"}], "equipment": []}]}], "creditsText": "Serious Eats"}