{"vegetarian": false, "vegan": false, "glutenFree": true, "dairyFree": true, "veryHealthy": false, "cheap": false, "veryPopular": false, "sustainable": false, "weightWatcherSmartPoints": 23, "gaps": "no", "lowFodmap": false, "ketogenic": false, "whole30": false, "sourceUrl": "http://www.seriouseats.com/recipes/2014/04/chicken-tinga-tacos-recipe.html", "spoonacularSourceUrl": "https://spoonacular.com/smoky-chicken-tinga-tacos-471622", "aggregateLikes": 30, "spoonacularScore": 67.0, "healthScore": 17.0, "creditText": "Serious Eats", "sourceName": "Serious Eats", "pricePerServing": 597.67, "extendedIngredients": [{"id": 6979, "aisle": "Ethnic Foods", "image": "harissa.jpg", "consitency": "solid", "name": "adobo sauce", "original": "2 tablespoons roughly chopped chipotles plus 2 tablespoons adobo sauce from one (7-ounce) can", "originalString": "2 tablespoons roughly chopped chipotles plus 2 tablespoons adobo sauce from one (7-ounce) can", "originalName": "tablespoons roughly chopped chipotles plus 2 tablespoons adobo sauce from one can", "amount": 7.0, "unit": "ounce", "meta": ["roughly chopped"], "metaInformation": ["roughly chopped"], "measures": {"us": {"amount": 7.0, "unitShort": "oz", "unitLong": "ounces"}, "metric": {"amount": 198.447, "unitShort": "g", "unitLong": "grams"}}}, {"id": 2004, "aisle": "Spices and Seasonings", "image": "bay-leaves.jpg", "consitency": "solid", "name": "bay leaf", "original": "1 bay leaf", "originalString": "1 bay leaf", "originalName": "bay leaf", "amount": 1.0, "unit": "", "meta": [], "metaInformation": [], "measures": {"us": {"amount": 1.0, "unitShort": "", "unitLong": ""}, "metric": {"amount": 1.0, "unitShort": "", "unitLong": ""}}}, {"id": 10011693, "aisle": "Canned and Jarred", "image": "tomatoes-canned.png", "consitency": "solid", "name": "canned tomatoes", "original": "1 (14.5-ounce) can fire-roasted diced or crushed tomatoes", "originalString": "1 (14.5-ounce) can fire-roasted diced or crushed tomatoes", "originalName": "fire-roasted diced or crushed tomatoes", "amount": 14.5, "unit": "ounce", "meta": ["diced", "crushed", "canned"], "metaInformation": ["diced", "crushed", "canned"], "measures": {"us": {"amount": 14.5, "unitShort": "oz", "unitLong": "ounces"}, "metric": {"amount": 411.068, "unitShort": "g", "unitLong": "grams"}}}, {"id": 18363, "aisle": "Bakery/Bread;Pasta and Rice;Ethnic Foods", "image": "flour-tortilla.jpg", "consitency": "solid", "name": "corn tortillas", "original": "Warm corn tortillas, tomatillo salsa, onion, cilantro, grated cotija cheese, and llime wedges for serving", "originalString": "Warm corn tortillas, tomatillo salsa, onion, cilantro, grated cotija cheese, and llime wedges for serving", "originalName": "Warm corn tortillas, tomatillo salsa, onion, cilantro, grated cotija cheese, and llime wedges for serving", "amount": 4.0, "unit": "servings", "meta": ["grated", "for serving"], "metaInformation": ["grated", "for serving"], "measures": {"us": {"amount": 4.0, "unitShort": "servings", "unitLong": "servings"}, "metric": {"amount": 4.0, "unitShort": "servings", "unitLong": "servings"}}}, {"id": 11215, "aisle": "Produce", "image": "garlic.jpg", "consitency": "solid", "name": "garlic", "original": "2 medium cloves garlic, smashed and peeled", "originalString": "2 medium cloves garlic, smashed and peeled", "originalName": "garlic, smashed and peeled", "amount": 2.0, "unit": "medium cloves", "meta": ["peeled", "smashed"], "metaInformation": ["peeled", "smashed"], "measures": {"us": {"amount": 2.0, "unitShort": "medium cloves", "unitLong": "medium cloves"}, "metric": {"amount": 2.0, "unitShort": "medium cloves", "unitLong": "medium cloves"}}}, {"id": 1002014, "aisle": "Spices and Seasonings", "image": "ground-cumin.jpg", "consitency": "solid", "name": "ground cumin", "original": "1/4 teaspoon ground cumin", "originalString": "1/4 teaspoon ground cumin", "originalName": "ground cumin", "amount": 0.25, "unit": "teaspoon", "meta": [], "metaInformation": [], "measures": {"us": {"amount": 0.25, "unitShort": "tsps", "unitLong": "teaspoons"}, "metric": {"amount": 0.25, "unitShort": "tsps", "unitLong": "teaspoons"}}}, {"id": 1082047, "aisle": "Spices and Seasonings", "image": "salt.jpg", "consitency": "solid", "name": "kosher salt", "original": "Kosher salt", "originalString": "Kosher salt", "originalName": "Kosher salt", "amount": 4.0, "unit": "servings", "meta": [], "metaInformation": [], "measures": {"us": {"amount": 4.0, "unitShort": "servings", "unitLong": "servings"}, "metric": {"amount": 4.0, "unitShort": "servings", "unitLong": "servings"}}}, {"id": 6970, "aisle": "Canned and Jarred", "image": "chicken-broth.png", "consitency": "liquid", "name": "low sodium chicken broth", "original": "1/2 cup homemade chicken stock or low-sodium chicken broth", "originalString": "1/2 cup homemade chicken stock or low-sodium chicken broth", "originalName": "homemade chicken stock or low-sodium chicken broth", "amount": 0.5, "unit": "cup", "meta": ["low-sodium", "homemade"], "metaInformation": ["low-sodium", "homemade"], "measures": {"us": {"amount": 0.5, "unitShort": "cups", "unitLong": "cups"}, "metric": {"amount": 118.294, "unitShort": "g", "unitLong": "grams"}}}, {"id": 4053, "aisle": "Oil, Vinegar, Salad Dressing", "image": "olive-oil.jpg", "consitency": "liquid", "name": "olive oil", "original": "1 tablespoon extra-virgin olive oil", "originalString": "1 tablespoon extra-virgin olive oil", "originalName": "extra-virgin olive oil", "amount": 1.0, "unit": "tablespoon", "meta": ["extra-virgin"], "metaInformation": ["extra-virgin"], "measures": {"us": {"amount": 1.0, "unitShort": "Tbsp", "unitLong": "Tbsp"}, "metric": {"amount": 1.0, "unitShort": "Tbsp", "unitLong": "Tbsp"}}}, {"id": 2027, "aisle": "Produce;Spices and Seasonings", "image": "oregano.jpg", "consitency": "solid", "name": "oregano", "original": "1/2 teaspoon Mexican oregano", "originalString": "1/2 teaspoon Mexican oregano", "originalName": "Mexican oregano", "amount": 0.5, "unit": "teaspoon", "meta": [], "metaInformation": [], "measures": {"us": {"amount": 0.5, "unitShort": "tsps", "unitLong": "teaspoons"}, "metric": {"amount": 0.5, "unitShort": "tsps", "unitLong": "teaspoons"}}}, {"id": 98891, "aisle": "Ethnic Foods", "image": "beancurd-sheets.jpg", "consitency": "solid", "name": "tofu skin", "original": "1 1/2 pounds skin-on, bone-in chicken thighs", "originalString": "1 1/2 pounds skin-on, bone-in chicken thighs", "originalName": "skin-on, bone-in chicken thighs", "amount": 1.5, "unit": "pounds", "meta": ["bone-in"], "metaInformation": ["bone-in"], "measures": {"us": {"amount": 1.5, "unitShort": "lb", "unitLong": "pounds"}, "metric": {"amount": 680.389, "unitShort": "g", "unitLong": "grams"}}}, {"id": 11954, "aisle": "Produce", "image": "tomatillos.jpg", "consitency": "solid", "name": "tomatillo", "original": "1 large tomatillo, husk removed, rinsed, and roughly chopped", "originalString": "1 large tomatillo, husk removed, rinsed, and roughly chopped", "originalName": "tomatillo, husk removed, rinsed, and roughly chopped", "amount": 1.0, "unit": "large", "meta": ["rinsed", "roughly chopped"], "metaInformation": ["rinsed", "roughly chopped"], "measures": {"us": {"amount": 1.0, "unitShort": "large", "unitLong": "large"}, "metric": {"amount": 1.0, "unitShort": "large", "unitLong": "large"}}}, {"id": 10611282, "aisle": "Produce", "image": "white-onion.png", "consitency": "solid", "name": "white onion", "original": "1 cup medium diced white onion", "originalString": "1 cup medium diced white onion", "originalName": "diced white onion", "amount": 1.0, "unit": "cup", "meta": ["diced", "white"], "metaInformation": ["diced", "white"], "measures": {"us": {"amount": 1.0, "unitShort": "cup", "unitLong": "cup"}, "metric": {"amount": 236.588, "unitShort": "g", "unitLong": "grams"}}}], "id": 471622, "title": "Smoky Chicken Tinga Tacos", "readyInMinutes": 60, "servings": 4, "image": "https://spoonacular.com/recipeImages/471622-556x370.jpg", "imageType": "jpg", "cuisines": ["mexican"], "dishTypes": ["lunch", "main course", "main dish", "dinner"], "diets": ["gluten free", "dairy free"], "occasions": [], "winePairing": {"pairedWines": ["pinot noir", "riesling", "sparkling rose"], "pairingText": "Pinot Noir, Riesling, and Sparkling ros\u00e9 are my top picks for Mexican. Acidic white wines like riesling or low-tannin reds like pinot noir can work well with Mexican dishes. Sparkling ros\u00e9 is a safe pairing too. The David Bruce Russian River Pinot Noir with a 4 out of 5 star rating seems like a good match. It costs about 30 dollars per bottle.", "productMatches": [{"id": 441990, "title": "David Bruce Russian River Pinot Noir", "description": "Sour cherries, ripe white cherries, sage and white pepper with a hint of angelica. An earthy mineral and graphite flavor joins the dry raspberry and plum notes, giving this a savory edge.", "price": "$29.99", "imageUrl": "https://spoonacular.com/productImages/441990-312x231.jpg", "averageRating": 0.8, "ratingCount": 5.0, "score": 0.7375, "link": "https://click.linksynergy.com/deeplink?id=*QCiIS6t4gA&mid=2025&murl=https%3A%2F%2Fwww.wine.com%2Fproduct%2Fdavid-bruce-russian-river-pinot-noir-2009%2F114432"}]}, "instructions": "Procedures                                                                              1                                                                                                                                                                                                                                                                                                                                                                                                                                                                                                 Heat oil in a Dutch oven or large pot over medium-high heat until shimmering. Add chicken thighs skin-side down and cook until well browned, about 6 minutes. Flip thighs and continue to cook until other side is lightly browned, about 3 minutes. Transfer chicken to a plate, leaving fat in pan, and set aside.                                                                                                                            2                                                                                                                                                                                                                                                                                                                                                                                                                                                                                                 Add onions and garlic to Dutch oven and cook, stirring occasionally, until onions have browned around the edges, about 5 minutes. Add tomatillo and cook until browned around the edges, about 4 minutes. Add oregano and cumin and cook until fragrant, about 30 seconds. Add tomatoes, chipotle, and adobo sauce and stir to combine. Remove from heat.                                                                                                                            3                                                                                                                                                                                                                                                                                                                                                                                                                                                                                                 Transfer sauce to the jar of a blender and puree until smooth. Pour sauce back into pan, stir in chicken stock and bay leaf, and bring to a boil over medium heat. Nestle chicken thighs in sauce, reduce to a simmer, and cook until meat registers 165\u00b0F in thickest part of thigh on an instant-read thermometer. Transfer chicken to a plate and let sit until cool enough to handle. Remove sauce from heat and discard bay leaf.                                                                                                                            4                                                                                                                                                                                                                                                                                                                                                                                                                                                                                                 Pull chicken meat into strips, discarding skin, any large pieces of fat, and bones. Stir chicken into sauce and cook over medium heat until warmed through, about 3 minutes. Remove from heat and season with salt to taste.                                                                                                                            5                                                                                                                                                                                                                                                                                                                                                                                                                                                                                                 Spoon chicken into warm tortillas and top with tomatillo salsa, onion, cilantro, and cotija cheese. Serve with lime wedges.", "analyzedInstructions": [{"name": "", "steps": [{"number": 1, "step": "Heat oil in a Dutch oven or large pot over medium-high heat until shimmering.", "ingredients": [], "equipment": [{"id": 404667, "name": "dutch oven", "image": "dutch-oven.jpg"}]}, {"number": 2, "step": "Add chicken thighs skin-side down and cook until well browned, about 6 minutes. Flip thighs and continue to cook until other side is lightly browned, about 3 minutes.", "ingredients": [], "equipment": [], "length": {"number": 9, "unit": "minutes"}}, {"number": 3, "step": "Transfer chicken to a plate, leaving fat in pan, and set aside.", "ingredients": [], "equipment": [{"id": 404645, "name": "frying pan", "image": "pan.png"}]}, {"number": 4, "step": "Add onions and garlic to Dutch oven and cook, stirring occasionally, until onions have browned around the edges, about 5 minutes.", "ingredients": [{"id": 11215, "name": "garlic", "image": "garlic.png"}, {"id": 11282, "name": "onion", "image": "brown-onion.png"}], "equipment": [{"id": 404667, "name": "dutch oven", "image": "dutch-oven.jpg"}], "length": {"number": 5, "unit": "minutes"}}, {"number": 5, "step": "Add tomatillo and cook until browned around the edges, about 4 minutes.", "ingredients": [{"id": 11954, "name": "tomatillos", "image": "tomatillos.jpg"}], "equipment": [], "length": {"number": 4, "unit": "minutes"}}, {"number": 6, "step": "Add oregano and cumin and cook until fragrant, about 30 seconds.", "ingredients": [{"id": 2027, "name": "oregano", "image": "oregano.jpg"}, {"id": 1002014, "name": "cumin", "image": "ground-cumin.jpg"}], "equipment": []}, {"number": 7, "step": "Add tomatoes, chipotle, and adobo sauce and stir to combine.", "ingredients": [{"id": 6979, "name": "adobo sauce", "image": "harissa.jpg"}], "equipment": []}, {"number": 8, "step": "Remove from heat.", "ingredients": [], "equipment": []}, {"number": 9, "step": "Transfer sauce to the jar of a blender and puree until smooth.", "ingredients": [], "equipment": [{"id": 404726, "name": "blender", "image": "blender.png"}]}, {"number": 10, "step": "Pour sauce back into pan, stir in chicken stock and bay leaf, and bring to a boil over medium heat. Nestle chicken thighs in sauce, reduce to a simmer, and cook until meat registers 165\u00b0F in thickest part of thigh on an instant-read thermometer.", "ingredients": [{"id": 2004, "name": "bay leaves", "image": "bay-leaves.jpg"}], "equipment": [{"id": 404789, "name": "kitchen thermometer", "image": "food-thermometer.jpg"}, {"id": 404645, "name": "frying pan", "image": "pan.png"}]}, {"number": 11, "step": "Transfer chicken to a plate and let sit until cool enough to handle.", "ingredients": [], "equipment": []}, {"number": 12, "step": "Remove sauce from heat and discard bay leaf.", "ingredients": [{"id": 2004, "name": "bay leaves", "image": "bay-leaves.jpg"}], "equipment": []}, {"number": 13, "step": "Pull chicken meat into strips, discarding skin, any large pieces of fat, and bones. Stir chicken into sauce and cook over medium heat until warmed through, about 3 minutes.", "ingredients": [], "equipment": [], "length": {"number": 3, "unit": "minutes"}}, {"number": 14, "step": "Remove from heat and season with salt to taste.", "ingredients": [{"id": 2047, "name": "salt", "image": "salt.jpg"}], "equipment": []}, {"number": 15, "step": "Spoon chicken into warm tortillas and top with tomatillo salsa, onion, cilantro, and cotija cheese.", "ingredients": [{"id": 11282, "name": "onion", "image": "brown-onion.png"}], "equipment": []}, {"number": 16, "step": "Serve with lime wedges.", "ingredients": [], "equipment": []}]}], "creditsText": "Serious Eats"}