{"vegetarian": false, "vegan": false, "glutenFree": false, "dairyFree": false, "veryHealthy": false, "cheap": false, "veryPopular": false, "sustainable": false, "weightWatcherSmartPoints": 21, "gaps": "no", "lowFodmap": false, "ketogenic": false, "whole30": false, "preparationMinutes": 20, "cookingMinutes": 40, "sourceUrl": "http://momsdish.com/recipe/38/turkey-macaroni-casserole", "spoonacularSourceUrl": "https://spoonacular.com/turkey-macaroni-casserole-511378", "aggregateLikes": 23, "spoonacularScore": 84.0, "healthScore": 28.0, "creditText": "Moms Dish", "sourceName": "Moms Dish", "pricePerServing": 374.48, "extendedIngredients": [{"id": 11215, "aisle": "Produce", "image": "garlic.jpg", "consitency": "solid", "name": "garlic", "original": "1 tablespoon Garlic; diced", "originalString": "1 tablespoon Garlic; diced", "originalName": "Garlic; diced", "amount": 1.0, "unit": "tablespoon", "meta": ["diced"], "metaInformation": ["diced"], "measures": {"us": {"amount": 1.0, "unitShort": "Tbsp", "unitLong": "Tbsp"}, "metric": {"amount": 1.0, "unitShort": "Tbsp", "unitLong": "Tbsp"}}}, {"id": 5662, "aisle": "Meat", "image": "meat-ground.jpg", "consitency": "solid", "name": "ground turkey", "original": "2 pounds Ground Turkey", "originalString": "2 pounds Ground Turkey", "originalName": "Ground Turkey", "amount": 2.0, "unit": "pounds", "meta": [], "metaInformation": [], "measures": {"us": {"amount": 2.0, "unitShort": "lb", "unitLong": "pounds"}, "metric": {"amount": 907.185, "unitShort": "g", "unitLong": "grams"}}}, {"id": 1001025, "aisle": "Cheese", "image": "shredded-cheese-white.jpg", "consitency": "solid", "name": "jack cheese", "original": "3 cups Jack/Cheddar Cheese; grated", "originalString": "3 cups Jack/Cheddar Cheese; grated", "originalName": "Jack/Cheddar Cheese; grated", "amount": 3.0, "unit": "cups", "meta": ["grated"], "metaInformation": ["grated"], "measures": {"us": {"amount": 3.0, "unitShort": "cups", "unitLong": "cups"}, "metric": {"amount": 709.764, "unitShort": "g", "unitLong": "grams"}}}, {"id": 20499, "aisle": "Pasta and Rice", "image": "macaroni.png", "consitency": "solid", "name": "macaroni", "original": "1 pound Macaroni", "originalString": "1 pound Macaroni", "originalName": "Macaroni", "amount": 1.0, "unit": "pound", "meta": [], "metaInformation": [], "measures": {"us": {"amount": 1.0, "unitShort": "lb", "unitLong": "pound"}, "metric": {"amount": 453.592, "unitShort": "g", "unitLong": "grams"}}}, {"id": 11282, "aisle": "Produce", "image": "brown-onion.png", "consitency": "solid", "name": "onions", "original": "2 cups Onions; diced", "originalString": "2 cups Onions; diced", "originalName": "Onions; diced", "amount": 2.0, "unit": "cups", "meta": ["diced"], "metaInformation": ["diced"], "measures": {"us": {"amount": 2.0, "unitShort": "cups", "unitLong": "cups"}, "metric": {"amount": 473.176, "unitShort": "g", "unitLong": "grams"}}}, {"id": 10011549, "aisle": "Pasta and Rice", "image": "tomato-sauce-or-pasta-sauce.jpg", "consitency": "solid", "name": "pasta sauce", "original": "16 ounces Pasta Sauce", "originalString": "16 ounces Pasta Sauce", "originalName": "Pasta Sauce", "amount": 16.0, "unit": "ounces", "meta": [], "metaInformation": [], "measures": {"us": {"amount": 16.0, "unitShort": "oz", "unitLong": "ounces"}, "metric": {"amount": 453.592, "unitShort": "g", "unitLong": "grams"}}}, {"id": 1102047, "aisle": "Spices and Seasonings", "image": "salt-and-pepper.jpg", "consitency": "solid", "name": "Salt & Pepper", "original": "Salt & Pepper; to taste", "originalString": "Salt & Pepper; to taste", "originalName": "Salt & Pepper; to taste", "amount": 6.0, "unit": "servings", "meta": ["to taste"], "metaInformation": ["to taste"], "measures": {"us": {"amount": 6.0, "unitShort": "servings", "unitLong": "servings"}, "metric": {"amount": 6.0, "unitShort": "servings", "unitLong": "servings"}}}, {"id": 4513, "aisle": "Oil, Vinegar, Salad Dressing", "image": "vegetable-oil.jpg", "consitency": "liquid", "name": "vegetable oil", "original": "2 tablespoons Vegetable Oil", "originalString": "2 tablespoons Vegetable Oil", "originalName": "Vegetable Oil", "amount": 2.0, "unit": "tablespoons", "meta": [], "metaInformation": [], "measures": {"us": {"amount": 2.0, "unitShort": "Tbsps", "unitLong": "Tbsps"}, "metric": {"amount": 2.0, "unitShort": "Tbsps", "unitLong": "Tbsps"}}}], "id": 511378, "title": "Turkey Macaroni Casserole", "readyInMinutes": 60, "servings": 6, "image": "https://spoonacular.com/recipeImages/511378-556x370.jpg", "imageType": "jpg", "cuisines": [], "dishTypes": ["lunch", "main course", "main dish", "dinner"], "diets": [], "occasions": ["fall", "winter"], "winePairing": {"pairedWines": [], "pairingText": "No one wine will suit every pasta dish. Pasta in a tomato-based sauce will usually work well with a medium-bodied red, such as a montepulciano or chianti. Pasta with seafood or pesto will fare better with a light-bodied white, such as a pinot grigio. Cheese-heavy pasta can pair well with red or white - you might try a sangiovese wine for hard cheeses and a chardonnay for soft cheeses. We may be able to make a better recommendation if you ask again with a specific pasta dish.", "productMatches": []}, "instructions": "Heat the oven to 350 degrees F. Cook the macaroni for about 10 minutes on high heat; drain and set aside. Heat the oil in a skillet; add onion, and garlic, and saute until soft. Add the ground turkey and saute until browned. Add salt and pepper, to taste. In a large bowl, combine the macaroni and the turkey mixture. Spread this mixture into a 9 by 13-inch baking dish. Top with the cheese.Bake at 350F for 25 minutes.", "analyzedInstructions": [{"name": "", "steps": [{"number": 1, "step": "Heat the oven to 350 degrees F. Cook the macaroni for about 10 minutes on high heat; drain and set aside.", "ingredients": [{"id": 20499, "name": "macaroni", "image": "macaroni.png"}], "equipment": [{"id": 404784, "name": "oven", "image": "oven.jpg", "temperature": {"number": 350.0, "unit": "Fahrenheit"}}], "length": {"number": 10, "unit": "minutes"}}, {"number": 2, "step": "Heat the oil in a skillet; add onion, and garlic, and saute until soft.", "ingredients": [{"id": 11215, "name": "garlic", "image": "garlic.png"}, {"id": 11282, "name": "onion", "image": "brown-onion.png"}], "equipment": [{"id": 404645, "name": "frying pan", "image": "pan.png"}]}, {"number": 3, "step": "Add the ground turkey and saute until browned.", "ingredients": [{"id": 5662, "name": "ground turkey", "image": "meat-ground.jpg"}], "equipment": []}, {"number": 4, "step": "Add salt and pepper, to taste. In a large bowl, combine the macaroni and the turkey mixture.", "ingredients": [{"id": 1102047, "name": "salt and pepper", "image": "salt-and-pepper.jpg"}, {"id": 20499, "name": "macaroni", "image": "macaroni.png"}], "equipment": [{"id": 404783, "name": "bowl", "image": "bowl.jpg"}]}, {"number": 5, "step": "Spread this mixture into a 9 by 13-inch baking dish. Top with the cheese.", "ingredients": [], "equipment": [{"id": 404646, "name": "baking pan", "image": "roasting-pan.jpg"}]}, {"number": 6, "step": "Bake at 350F for 25 minutes.", "ingredients": [], "equipment": [], "length": {"number": 25, "unit": "minutes"}}]}], "creditsText": "Moms Dish"}